RTL/smii_phy_if.sv

//--------------------------------------------------------------------------------------------------------
// Module  : smii_phy_if
// Type    : synthesizable, IP's top
// Standard: SystemVerilog 2005 (IEEE1800-2005)
// Function: MII (MAC side) to SMII (PHY side) converter, for 10M or 100M ethernet
//--------------------------------------------------------------------------------------------------------

module smii_phy_if #(
    parameter  RX_SYNC_DELAY = 1  // Considering the PCB delay, when phy_smii_sync propagates from FPGA to PHY, and phy_smii_rxd propagates from PHY back to FPGA, phy_smii_rxd may be one cycle later than phy_smii_sync in FPGA's view. 
                                  // To compensate for the PCB delay, you can set this parameter to 1 to add one cycle delay to phy_smii_sync during the phy_smii_rxd sampling to compensate for the PCB delay.
                                  // 0: no delay
                                  // 1: one cycle delay
) (
    // reset, active low
    input  wire       rstn_async,
    // status output (optional for user)
    output reg        mode_speed,        // 0:10M,  1:100M
    output reg        mode_duplex,       // 0:Half, 1:Full
    output reg        status_link,       // 0:Link down   1: Link up
    // MII interface connect to MAC
    output reg        mac_mii_crs,
    output wire       mac_mii_rxrst,     // optional reset signal to MAC
    output reg        mac_mii_rxc,
    output reg        mac_mii_rxdv,
    output wire       mac_mii_rxer,
    output reg  [3:0] mac_mii_rxd,
    output wire       mac_mii_txrst,     // optional reset signal to MAC
    output wire       mac_mii_txc,
    input  wire       mac_mii_txen,
    input  wire       mac_mii_txer,
    input  wire [3:0] mac_mii_txd,
    // SMII interface connect to  PHY
    input  wire       phy_smii_ref_clk,  // 125MHz required
    output reg        phy_smii_sync,
    input  wire       phy_smii_rxd,
    output reg        phy_smii_txd
);

initial {mode_speed, mode_duplex, status_link} = '0;
initial {mac_mii_crs, mac_mii_rxc, mac_mii_rxdv, mac_mii_rxd} = '0;
initial {phy_smii_sync, phy_smii_txd} = '0;

reg [3:0] tx_rst_r = 4'hf;
reg       smii_rxsync_p = 1'b0;
reg       smii_rxsync = 1'b0;
reg       smii_rxd = 1'b0;
reg [6:0] rx_cnt = 4'h0;
reg       rx_crs = 1'b0;
reg       rx_dv = 1'b0;
reg [6:0] rx_data = 7'h0;
reg       rx_data_msb = 1'b0;
reg       rx_dv_r = 1'b0;
reg [7:0] rx_data_r = 8'h0;
reg       mii_txc_r = 1'b0;
wire      mii_txc_negedge;
reg       tx_en_r = 1'b0;
reg       tx_even = 1'b0;
reg       tx_err = 1'b0;
reg [3:0] tx_nibble = 4'h0;
reg [9:0] tx_serial = 10'b1110111000;
reg [4:0] tx_cnt = 4'd1;
reg [4:0] tx_seg_cnt = 4'd1;
reg [9:0] tx_serial_r = 10'h0;
reg       smii_txsync = 1'b0;
reg       smii_txd = 1'b0;

// ----------------------------------------------------------------------------------------------------------------------
//  reset sync
// ----------------------------------------------------------------------------------------------------------------------
reg       rstn = '0;
reg [7:0] rstn_shift = '0;
always @ (posedge phy_smii_ref_clk or negedge rstn_async)
    if(~rstn_async)
        {rstn, rstn_shift} <= '0;
    else
        {rstn, rstn_shift} <= {rstn_shift, 1'b1};

// ----------------------------------------------------------------------------------------------------------------------
//  SMII TX reset and RX reset generate to MAC
// ----------------------------------------------------------------------------------------------------------------------
assign mac_mii_rxrst = ~rstn;
assign mac_mii_txrst = tx_rst_r[0];
always @ (posedge phy_smii_ref_clk or negedge rstn)
    if(~rstn) begin
        tx_rst_r <= 4'hf;
    end else begin
        if(phy_smii_sync) begin
            tx_rst_r <= {1'b0, tx_rst_r[3:1]};
        end
    end

// ----------------------------------------------------------------------------------------------------------------------
//  SMII RX latch pre
// ----------------------------------------------------------------------------------------------------------------------
always @ (posedge phy_smii_ref_clk or negedge rstn)
    if(~rstn) begin
        smii_rxsync_p <= 1'b0;
    end else begin
        smii_rxsync_p <= phy_smii_sync;
    end

// ----------------------------------------------------------------------------------------------------------------------
//  SMII RX latch
// ----------------------------------------------------------------------------------------------------------------------
always @ (posedge phy_smii_ref_clk or negedge rstn)
    if(~rstn) begin
        smii_rxsync <= 1'b0;
        smii_rxd <= 1'b0;
    end else begin
        smii_rxsync <= (RX_SYNC_DELAY==0) ? phy_smii_sync : smii_rxsync_p;
        smii_rxd <= phy_smii_rxd;
    end

// ----------------------------------------------------------------------------------------------------------------------
//  SMII RX parse
// ----------------------------------------------------------------------------------------------------------------------
always @ (posedge phy_smii_ref_clk or negedge rstn)
    if(~rstn) begin
        rx_cnt <= 7'd0;
        rx_crs <= 1'b0;
        rx_dv <= 1'b0;
        rx_data <= 7'h0;
        rx_data_msb <= 1'b0;
        rx_dv_r <= 1'b0;
        rx_data_r <= 8'h0;
        mode_speed <= 1'b0;
        mode_duplex <= 1'b0;
        status_link <= 1'b0;
        mac_mii_crs <= 1'b0;
    end else begin
        if( rx_cnt == 7'd0 ) begin
            if(smii_rxsync) begin
                rx_cnt <= 7'd1;
                rx_crs <= smii_rxd;
            end
        end else if( rx_cnt == 7'd1 ) begin
            rx_cnt <= 7'd2;
            rx_dv <= smii_rxd;
        end else if( rx_cnt <  7'd9 ) begin
            rx_cnt <= rx_cnt + 7'd1;
            rx_data <= {smii_rxd, rx_data[6:1]};
        end else if( rx_cnt == 7'd9 ) begin
            if( rx_dv ) begin
                rx_cnt <= mode_speed ? 7'd0 : 7'd10;
                if(mode_speed) begin
                    rx_dv_r <= 1'b1;
                    rx_data_r <= {smii_rxd, rx_data};
                end
            end else begin
                rx_cnt <= rx_data[1] ? 7'd0 : 7'd10;
                if(rx_data[1]) begin
                    rx_dv_r <= 1'b0;
                    rx_data_r <= 8'h0;
                end
                mode_speed <= rx_data[1];
                mode_duplex <= rx_data[2];
                status_link <= rx_data[3];
            end
            rx_data_msb <= smii_rxd;
            mac_mii_crs <= rx_crs;
        end else if( rx_cnt < 7'd99 ) begin
            rx_cnt <= rx_cnt + 7'd1;
        end else begin
            rx_cnt <= 7'd0;
            rx_dv_r <= rx_dv;
            rx_data_r <= rx_dv ? {rx_data_msb, rx_data} : 8'h0;
        end
    end

// ----------------------------------------------------------------------------------------------------------------------
//  MII RX generate
// ----------------------------------------------------------------------------------------------------------------------
assign mac_mii_rxer = 1'b0;
always @ (posedge phy_smii_ref_clk or negedge rstn)
    if(~rstn) begin
        mac_mii_rxc <= 1'b0;
        mac_mii_rxdv <= 1'b0;
        mac_mii_rxd <= 4'h0;
    end else begin
        if( mode_speed ) begin
            mac_mii_rxc <= (rx_cnt==7'd3) || (rx_cnt==7'd4) || (rx_cnt==7'd8) || (rx_cnt==7'd9);
            if( rx_cnt == 7'd0 ) begin
                mac_mii_rxdv <= rx_dv_r;
                mac_mii_rxd <= rx_data_r[3:0];
            end else if( rx_cnt == 7'd5 ) begin
                mac_mii_rxd <= rx_data_r[7:4];
            end
        end else begin
            mac_mii_rxc <= (rx_cnt>=7'd25 && rx_cnt<=7'd49) || (rx_cnt>=7'd75);
            if( rx_cnt == 7'd0 ) begin
                mac_mii_rxdv <= rx_dv_r;
                mac_mii_rxd <= rx_data_r[3:0];
            end else if( rx_cnt == 7'd50 ) begin
                mac_mii_rxd <= rx_data_r[7:4];
            end
        end
    end

// ----------------------------------------------------------------------------------------------------------------------
//  MII TX clock generate
// ----------------------------------------------------------------------------------------------------------------------
assign mac_mii_txc = mac_mii_rxc;

// ----------------------------------------------------------------------------------------------------------------------
//  MII TX clock negedge detect
// ----------------------------------------------------------------------------------------------------------------------
assign mii_txc_negedge = mii_txc_r & ~mac_mii_txc;
always @ (posedge phy_smii_ref_clk or negedge rstn)
    if(~rstn)
        mii_txc_r <= 1'b0;
    else
        mii_txc_r <= mac_mii_txc;

// ----------------------------------------------------------------------------------------------------------------------
//  MII TX parse
// ----------------------------------------------------------------------------------------------------------------------
always @ (posedge phy_smii_ref_clk or negedge rstn)
    if(~rstn) begin
        tx_en_r <= 1'b0;
        tx_even <= 1'b0;
        tx_err <= 1'b0;
        tx_nibble <= 4'h0;
        tx_serial <= 10'b1110111000;
    end else begin
        if(mii_txc_negedge) begin
            tx_en_r <= mac_mii_txen;
            if(tx_even & tx_en_r & mac_mii_txen) begin
                tx_even <= 1'b0;
                tx_serial <= {mac_mii_txd, tx_nibble, 1'b1, tx_err|mac_mii_txer};
            end else begin
                tx_even <= mac_mii_txen | ~tx_even;
                tx_err <= mac_mii_txer;
                tx_nibble <= mac_mii_txd;
                if(tx_even)
                    tx_serial <= 10'b1110111000;
            end
        end
    end

// ----------------------------------------------------------------------------------------------------------------------
//  SMII TX count
// ----------------------------------------------------------------------------------------------------------------------
always @ (posedge phy_smii_ref_clk or negedge rstn)
    if(~rstn) begin
        tx_cnt <= 4'd1;
        tx_seg_cnt <= 4'd1;
        tx_serial_r <= 10'd0;
    end else begin
        if(tx_cnt<4'd9) begin
            tx_cnt <= tx_cnt + 4'd1;
        end else begin
            tx_cnt <= 4'd0;
            if( tx_seg_cnt < 4'd9 && ~mode_speed ) begin
                tx_seg_cnt <= tx_seg_cnt + 4'd1;
            end else begin
                tx_seg_cnt <= 4'd0;
                tx_serial_r <= tx_serial;
            end
        end
    end

// ----------------------------------------------------------------------------------------------------------------------
//  SMII TX generate and SYNC generate
// ----------------------------------------------------------------------------------------------------------------------
always @ (posedge phy_smii_ref_clk or negedge rstn)
    if(~rstn) begin
        smii_txsync <= 1'b0;
        smii_txd <= 1'b0;
    end else begin
        smii_txsync <= tx_cnt == 4'd0;
        smii_txd <= tx_serial_r[tx_cnt];
    end

// ----------------------------------------------------------------------------------------------------------------------
//  SMII TX output latch
// ----------------------------------------------------------------------------------------------------------------------
always @ (posedge phy_smii_ref_clk or negedge rstn)
    if(~rstn) begin
        phy_smii_sync <= 1'b0;
        phy_smii_txd <= 1'b0;
    end else begin
        phy_smii_sync <= smii_txsync;
        phy_smii_txd <= smii_txd;
    end

endmodule

SIM/tb_smii_phy_if.sv

//--------------------------------------------------------------------------------------------------------
// Module  : tb_smii_phy_if
// Type    : simulation, top
// Standard: SystemVerilog 2005 (IEEE1800-2005)
// Function: testbench for smii_phy_if
//--------------------------------------------------------------------------------------------------------

`timescale 1ps/1ps

module tb_smii_phy_if();

initial $dumpvars(0, tb_smii_phy_if);

reg rstn=1'b0;
initial #25000 rstn=1'b1;

// PHY ref clock
reg phy_smii_ref_clk=1'b1;
always  #4000  phy_smii_ref_clk = ~phy_smii_ref_clk;     // 125MHz

// status
wire       mode_speed;        // 0:10M,  1:100M
wire       mode_duplex;       // 0:Half, 1:Full
wire       status_link;       // 0:Link down   1: Link up

// MII signals (MAC side)
wire       mac_mii_crs;
wire       mac_mii_rxrst;
wire       mac_mii_rxc;
wire       mac_mii_rxdv;
wire       mac_mii_rxer;
wire [3:0] mac_mii_rxd;
wire       mac_mii_txrst;
wire       mac_mii_txc;
reg        mac_mii_txen = '0;
reg        mac_mii_txer = '0;
reg  [3:0] mac_mii_txd = '0;

// SMII signals (PHY side)
wire       phy_smii_sync;
reg        phy_smii_rxd = '0;
wire       phy_smii_txd;

// MII to SMII converter
smii_phy_if #(
    .RX_SYNC_DELAY    ( 0                )
) smii_phy_if_i(
    .rstn_async       ( rstn             ),
    .mode_speed       ( mode_speed       ),
    .mode_duplex      ( mode_duplex      ),
    .status_link      ( status_link      ),
    .mac_mii_crs      ( mac_mii_crs      ),
    .mac_mii_rxrst    ( mac_mii_rxrst    ),
    .mac_mii_rxc      ( mac_mii_rxc      ),
    .mac_mii_rxdv     ( mac_mii_rxdv     ),
    .mac_mii_rxer     ( mac_mii_rxer     ),
    .mac_mii_rxd      ( mac_mii_rxd      ),
    .mac_mii_txrst    ( mac_mii_txrst    ),
    .mac_mii_txc      ( mac_mii_txc      ),
    .mac_mii_txen     ( mac_mii_txen     ),
    .mac_mii_txer     ( mac_mii_txer     ),
    .mac_mii_txd      ( mac_mii_txd      ),
    .phy_smii_ref_clk ( phy_smii_ref_clk ),
    .phy_smii_sync    ( phy_smii_sync    ),
    .phy_smii_rxd     ( phy_smii_rxd     ),
    .phy_smii_txd     ( phy_smii_txd     )
);

task automatic smii_phy_rx(input [9:0] data);
    while(~rstn) #1 ;
    while(~phy_smii_sync) #1 ;
    for(int i=0; i<10; i++) begin
        phy_smii_rxd <= data[i];
        @(posedge phy_smii_ref_clk);
    end
endtask

task automatic mii_mac_tx(input txen, input txer, input [3:0] txd);
    while(~rstn) #1 ;
    while(mac_mii_txrst) #1 ;
    mac_mii_txen <= txen;
    mac_mii_txer <= txer;
    mac_mii_txd <= txen ? txd : '0;
    @(posedge mac_mii_txc);
endtask


initial begin
    int i;
    fork
        begin
            smii_phy_rx(10'b1000101000);
            smii_phy_rx(10'b0000000111);
            smii_phy_rx(10'b0000001011);
            smii_phy_rx(10'b0000001110);
            smii_phy_rx(10'b1000101000);
            smii_phy_rx(10'b0000010111);
            smii_phy_rx(10'b0000011011);
            smii_phy_rx(10'b0000011110);
            smii_phy_rx(10'b0000100010);
            smii_phy_rx(10'b1000101000);
            smii_phy_rx(10'b1000101000);
            smii_phy_rx(10'b0000000111);
            smii_phy_rx(10'b0000001011);
            smii_phy_rx(10'b0000001110);
            smii_phy_rx(10'b1000101000);
            for(i=0; i<10; i++) smii_phy_rx(10'b1000100000);
            for(i=0; i<10; i++) smii_phy_rx(10'b1000100000);
            for(i=0; i<10; i++) smii_phy_rx(10'b0000000111);
            for(i=0; i<10; i++) smii_phy_rx(10'b0000001011);
            for(i=0; i<10; i++) smii_phy_rx(10'b0000001110);
            for(i=0; i<10; i++) smii_phy_rx(10'b1000100000);
            for(i=0; i<10; i++) smii_phy_rx(10'b0000010111);
            for(i=0; i<10; i++) smii_phy_rx(10'b0000011011);
            for(i=0; i<10; i++) smii_phy_rx(10'b0000011111);
            for(i=0; i<10; i++) smii_phy_rx(10'b0000100011);
            smii_phy_rx(10'b0000000000);
        end
        begin
            mii_mac_tx(1'b0, 1'b0, 4'h0);
            mii_mac_tx(1'b1, 1'b0, 4'h1);
            mii_mac_tx(1'b1, 1'b0, 4'h2);
            mii_mac_tx(1'b1, 1'b0, 4'h3);
            mii_mac_tx(1'b1, 1'b0, 4'h4);
            mii_mac_tx(1'b0, 1'b0, 4'h0);
            mii_mac_tx(1'b0, 1'b0, 4'h0);
            mii_mac_tx(1'b0, 1'b0, 4'h0);
            mii_mac_tx(1'b1, 1'b0, 4'h1);
            mii_mac_tx(1'b1, 1'b0, 4'h2);
            mii_mac_tx(1'b1, 1'b0, 4'h3);
            mii_mac_tx(1'b0, 1'b0, 4'h0);
            mii_mac_tx(1'b0, 1'b0, 4'h0);
            mii_mac_tx(1'b1, 1'b0, 4'h1);
            mii_mac_tx(1'b1, 1'b0, 4'h2);
            mii_mac_tx(1'b1, 1'b0, 4'h3);
            mii_mac_tx(1'b0, 1'b0, 4'h0);
            mii_mac_tx(1'b1, 1'b0, 4'h1);
            mii_mac_tx(1'b1, 1'b0, 4'h2);
            mii_mac_tx(1'b1, 1'b0, 4'h3);
            mii_mac_tx(1'b1, 1'b0, 4'h4);
            mii_mac_tx(1'b1, 1'b0, 4'h5);
            mii_mac_tx(1'b1, 1'b0, 4'h6);
            mii_mac_tx(1'b0, 1'b0, 4'h0);
            mii_mac_tx(1'b0, 1'b0, 4'h0);
            mii_mac_tx(1'b0, 1'b0, 4'h0);
            mii_mac_tx(1'b0, 1'b0, 4'h0);
            mii_mac_tx(1'b1, 1'b0, 4'h1);
            mii_mac_tx(1'b1, 1'b0, 4'h2);
            mii_mac_tx(1'b1, 1'b0, 4'h3);
            mii_mac_tx(1'b1, 1'b1, 4'h4);
            mii_mac_tx(1'b1, 1'b0, 4'h5);
            mii_mac_tx(1'b1, 1'b0, 4'h6);
            mii_mac_tx(1'b0, 1'b0, 4'h0);
            mii_mac_tx(1'b0, 1'b0, 4'h0);
            mii_mac_tx(1'b0, 1'b0, 4'h0);
            mii_mac_tx(1'b0, 1'b0, 4'h0);
            mii_mac_tx(1'b1, 1'b0, 4'h1);
            mii_mac_tx(1'b1, 1'b0, 4'h2);
            mii_mac_tx(1'b1, 1'b1, 4'h3);
            mii_mac_tx(1'b1, 1'b0, 4'h4);
            mii_mac_tx(1'b1, 1'b0, 4'h5);
            mii_mac_tx(1'b1, 1'b0, 4'h6);
            mii_mac_tx(1'b0, 1'b0, 4'h0);
            mii_mac_tx(1'b1, 1'b0, 4'h1);
            mii_mac_tx(1'b1, 1'b1, 4'h2);
            mii_mac_tx(1'b1, 1'b0, 4'h3);
            mii_mac_tx(1'b1, 1'b0, 4'h4);
            mii_mac_tx(1'b1, 1'b0, 4'h5);
            mii_mac_tx(1'b1, 1'b0, 4'h6);
            mii_mac_tx(1'b0, 1'b0, 4'h0);
            mii_mac_tx(1'b0, 1'b0, 4'h0);
            mii_mac_tx(1'b0, 1'b0, 4'h0);
            mii_mac_tx(1'b0, 1'b0, 4'h0);
            mii_mac_tx(1'b1, 1'b0, 4'h1);
            mii_mac_tx(1'b1, 1'b0, 4'h2);
            mii_mac_tx(1'b1, 1'b0, 4'h3);
            mii_mac_tx(1'b1, 1'b0, 4'h4);
            mii_mac_tx(1'b1, 1'b0, 4'h5);
            mii_mac_tx(1'b1, 1'b0, 4'h6);
            mii_mac_tx(1'b1, 1'b0, 4'h7);
            mii_mac_tx(1'b1, 1'b0, 4'h8);
            mii_mac_tx(1'b1, 1'b0, 4'h9);
            mii_mac_tx(1'b1, 1'b0, 4'ha);
            mii_mac_tx(1'b0, 1'b0, 4'h0);
        end
    join
    repeat(100) @ (posedge phy_smii_ref_clk);
    $stop;
end

endmodule

SIM/dump.vcd
$date
	Fri Mar 25 22:25:07 2022
$end
$version
	Icarus Verilog
$end
$timescale
	1ps
$end
$scope module tb_smii_phy_if $end
$var wire 1 ! mac_mii_rxer $end
$var wire 1 " status_link $end
$var wire 1 # phy_smii_txd $end
$var wire 1 $ phy_smii_sync $end
$var wire 1 % mode_speed $end
$var wire 1 & mode_duplex $end
$var wire 1 ' mac_mii_txrst $end
$var wire 1 ( mac_mii_txc $end
$var wire 1 ) mac_mii_rxrst $end
$var wire 1 * mac_mii_rxdv $end
$var wire 4 + mac_mii_rxd [3:0] $end
$var wire 1 , mac_mii_rxc $end
$var wire 1 - mac_mii_crs $end
$var reg 4 . mac_mii_txd [3:0] $end
$var reg 1 / mac_mii_txen $end
$var reg 1 0 mac_mii_txer $end
$var reg 1 1 phy_smii_ref_clk $end
$var reg 1 2 phy_smii_rxd $end
$var reg 1 3 rstn $end
$scope module smii_phy_if_i $end
$var wire 1 ! mac_mii_rxer $end
$var wire 1 ) mac_mii_rxrst $end
$var wire 1 ( mac_mii_txc $end
$var wire 4 4 mac_mii_txd [3:0] $end
$var wire 1 / mac_mii_txen $end
$var wire 1 0 mac_mii_txer $end
$var wire 1 5 mii_txc_negedge $end
$var wire 1 1 phy_smii_ref_clk $end
$var wire 1 2 phy_smii_rxd $end
$var wire 1 3 rstn_async $end
$var wire 1 ' mac_mii_txrst $end
$var reg 1 - mac_mii_crs $end
$var reg 1 , mac_mii_rxc $end
$var reg 4 6 mac_mii_rxd [3:0] $end
$var reg 1 * mac_mii_rxdv $end
$var reg 1 7 mii_txc_r $end
$var reg 1 & mode_duplex $end
$var reg 1 % mode_speed $end
$var reg 1 $ phy_smii_sync $end
$var reg 1 # phy_smii_txd $end
$var reg 1 8 rstn $end
$var reg 8 9 rstn_shift [7:0] $end
$var reg 7 : rx_cnt [6:0] $end
$var reg 1 ; rx_crs $end
$var reg 7 < rx_data [6:0] $end
$var reg 1 = rx_data_msb $end
$var reg 8 > rx_data_r [7:0] $end
$var reg 1 ? rx_dv $end
$var reg 1 @ rx_dv_r $end
$var reg 1 A smii_rxd $end
$var reg 1 B smii_rxsync $end
$var reg 1 C smii_rxsync_p $end
$var reg 1 D smii_txd $end
$var reg 1 E smii_txsync $end
$var reg 1 " status_link $end
$var reg 5 F tx_cnt [4:0] $end
$var reg 1 G tx_en_r $end
$var reg 1 H tx_err $end
$var reg 1 I tx_even $end
$var reg 4 J tx_nibble [3:0] $end
$var reg 4 K tx_rst_r [3:0] $end
$var reg 5 L tx_seg_cnt [4:0] $end
$var reg 10 M tx_serial [9:0] $end
$var reg 10 N tx_serial_r [9:0] $end
$upscope $end
$scope begin $unm_blk_2 $end
$var integer 32 O i [31:0] $end
$upscope $end
$scope task mii_mac_tx $end
$upscope $end
$scope task smii_phy_rx $end
$scope begin $ivl_for_loop0 $end
$upscope $end
$upscope $end
$upscope $end
$enddefinitions $end
#0
$dumpvars
b0 O
b0 N
b1110111000 M
b1 L
b1111 K
b0 J
0I
0H
0G
b1 F
0E
0D
0C
0B
0A
0@
0?
b0 >
0=
b0 <
0;
b0 :
b0 9
08
07
b0 6
05
b0 4
03
02
11
00
0/
b0 .
0-
0,
b0 +
0*
1)
0(
1'
0&
0%
0$
0#
0"
0!
$end
#4000
01
#8000
11
#12000
01
#16000
11
#20000
01
#24000
11
#25000
13
#28000
01
#32000
b1 9
11
#36000
01
#40000
b11 9
11
#44000
01
#48000
b111 9
11
#52000
01
#56000
b1111 9
11
#60000
01
#64000
b11111 9
11
#68000
01
#72000
b111111 9
11
#76000
01
#80000
b1111111 9
11
#84000
01
#88000
b11111111 9
11
#92000
01
#96000
0)
18
11
#100000
01
#104000
b10 F
11
#108000
01
#112000
b11 F
11
#116000
01
#120000
b100 F
11
#124000
01
#128000
b101 F
11
#132000
01
#136000
b110 F
11
#140000
01
#144000
b111 F
11
#148000
01
#152000
b1000 F
11
#156000
01
#160000
b1001 F
11
#164000
01
#168000
b10 L
b0 F
11
#172000
01
#176000
1E
b1 F
11
#180000
01
#184000
b10 F
0E
1$
11
#188000
01
#192000
0$
b11 F
1B
1C
b111 K
11
#196000
01
#200000
0C
0B
b1 :
b100 F
11
#204000
01
#208000
b101 F
b10 :
12
11
#212000
01
#216000
1A
b11 :
b110 F
02
11
#220000
01
#224000
b111 F
b1000000 <
b100 :
0A
12
11
#228000
01
#232000
1A
b100000 <
b101 :
b1000 F
02
11
#236000
01
#240000
b1001 F
b1010000 <
b110 :
0A
11
#244000
01
#248000
b101000 <
b111 :
b11 L
b0 F
11
#252000
01
#256000
1E
b1 F
b10100 <
b1000 :
12
11
#260000
01
#264000
1A
b1010 <
b1001 :
b10 F
0E
1$
11
#268000
01
#272000
0$
b11 F
1=
1"
1%
b0 :
1B
1C
b11 K
11
#276000
01
#280000
0C
0B
1;
b1 :
b100 F
11
#284000
01
#288000
b101 F
1?
b10 :
02
11
#292000
01
#296000
0A
b1000101 <
b11 :
b110 F
11
#300000
01
#304000
b111 F
1(
1,
b100010 <
b100 :
11
#308000
01
#312000
b10001 <
b101 :
17
b1000 F
11
#316000
01
#320000
15
b1001 F
0(
0,
b1000 <
b110 :
11
#324000
01
#328000
05
b100 <
b111 :
07
1I
b1110111000 N
b0 L
b0 F
11
#332000
01
#336000
1E
b1 F
b10 <
b1000 :
11
#340000
01
#344000
b1 <
b1001 :
1(
1,
b10 F
0E
1$
11
#344001
12
#348000
01
#352000
0$
b11 F
17
1-
0=
b1 >
1@
b0 :
1A
1B
1C
b1 K
11
#356000
01
#360000
15
0C
0B
b1 :
b1 +
b1 6
1*
0(
0,
b100 F
1D
02
11
#364000
01
#368000
05
1#
b101 F
0I
07
b10 :
0A
12
11
#372000
01
#376000
1A
b0 <
b11 :
b110 F
02
11
#380000
01
#384000
0D
b111 F
1(
1,
b1000000 <
b100 :
0A
11
#388000
01
#392000
b100000 <
b101 :
17
b1000 F
1D
0#
11
#396000
01
#400000
15
1#
b1001 F
b0 +
b0 6
0(
0,
b10000 <
b110 :
11
#404000
01
#408000
05
b1000 <
b111 :
07
1I
b0 F
11
#412000
01
#416000
0D
1E
b1 F
b100 <
b1000 :
11
#420000
01
#424000
b10 <
b1001 :
1(
1,
b10 F
0E
0#
1$
11
#428000
01
#432000
0'
0$
b11 F
17
b10 >
b0 :
1B
1C
b0 K
12
11
#436000
01
#440000
15
0C
1A
0B
0;
b1 :
b10 +
b10 6
0(
0,
b100 F
1D
11
#444000
01
#448000
05
1#
b101 F
0I
07
b10 :
11
#452000
01
#456000
b1000001 <
b11 :
b110 F
02
11
#460000
01
#464000
b1 .
b1 4
1/
0D
b111 F
1(
1,
b1100000 <
b100 :
0A
11
#468000
01
#472000
b110000 <
b101 :
17
b1000 F
1D
0#
11
#476000
01
#480000
15
1#
b1001 F
b0 +
b0 6
0(
0,
b11000 <
b110 :
11
#484000
01
#488000
05
b1100 <
b111 :
07
b1 J
1I
1G
b0 F
11
#492000
01
#496000
0D
1E
b1 F
b110 <
b1000 :
11
#500000
01
#504000
b10 .
b10 4
b11 <
b1001 :
1(
1,
b10 F
0E
0#
1$
11
#508000
01
#512000
0$
b11 F
17
0-
b11 >
b0 :
1B
1C
11
#516000
01
#520000
15
0C
0B
b1 :
b11 +
b11 6
0(
0,
b100 F
1D
11
#524000
01
#528000
05
1#
b101 F
b10000110 M
0I
07
0?
b10 :
12
11
#532000
01
#536000
1A
b1 <
b11 :
b110 F
02
11
#540000
01
#544000
b11 .
b11 4
0D
b111 F
1(
1,
b1000000 <
b100 :
0A
12
11
#548000
01
#552000
1A
b100000 <
b101 :
17
b1000 F
1D
0#
02
11
#556000
01
#560000
15
1#
b1001 F
b0 +
b0 6
0(
0,
b1010000 <
b110 :
0A
11
#564000
01
#568000
05
b101000 <
b111 :
07
b11 J
1I
b10000110 N
b0 F
11
#572000
01
#576000
0D
1E
b1 F
b10100 <
b1000 :
12
11
#580000
01
#584000
b100 .
b100 4
1A
b1010 <
b1001 :
1(
1,
b10 F
1D
0E
0#
1$
11
#588000
01
#592000
1#
0$
b11 F
17
1=
b0 >
0@
b0 :
1B
1C
11
#596000
01
#600000
15
0C
0B
1;
b1 :
0*
0(
0,
b100 F
0D
11
#604000
01
#608000
05
0#
b101 F
b100001110 M
0I
07
1?
b10 :
02
11
#612000
01
#616000
0A
b1000101 <
b11 :
b110 F
12
11
#620000
01
#624000
b0 .
b0 4
0/
b111 F
1(
1,
b100010 <
b100 :
1A
02
11
#628000
01
#632000
0A
b1010001 <
b101 :
17
b1000 F
1D
11
#636000
01
#640000
15
1#
0D
b1001 F
0(
0,
b101000 <
b110 :
11
#644000
01
#648000
05
b10100 <
b111 :
07
b0 J
1I
0G
b100001110 N
b0 F
0#
11
#652000
01
#656000
1E
b1 F
b1010 <
b1000 :
11
#660000
01
#664000
b101 <
b1001 :
1(
1,
b10 F
1D
0E
1$
11
#664001
12
#668000
01
#672000
1#
0$
b11 F
17
1-
0=
b101 >
1@
b0 :
1A
1B
1C
11
#676000
01
#680000
15
0C
0B
b1 :
b101 +
b101 6
1*
0(
0,
b100 F
02
11
#684000
01
#688000
05
0D
b101 F
b1110111000 M
0I
07
b10 :
0A
12
11
#692000
01
#696000
1A
b10 <
b11 :
b110 F
0#
11
#700000
01
#704000
b111 F
1(
1,
b1000001 <
b100 :
02
11
#708000
01
#712000
0A
b1100000 <
b101 :
17
b1000 F
11
#716000
01
#720000
15
1D
b1001 F
b0 +
b0 6
0(
0,
b110000 <
b110 :
11
#724000
01
#728000
05
b11000 <
b111 :
07
1I
b1110111000 N
b0 F
0D
1#
11
#732000
01
#736000
0#
1E
b1 F
b1100 <
b1000 :
11
#740000
01
#744000
b1 .
b1 4
1/
b110 <
b1001 :
1(
1,
b10 F
0E
1$
11
#748000
01
#752000
0$
b11 F
17
b110 >
b0 :
1B
1C
12
11
#756000
01
#760000
15
0C
1A
0B
0;
b1 :
b110 +
b110 6
0(
0,
b100 F
1D
11
#764000
01
#768000
05
1#
b101 F
b1 J
1G
07
b10 :
11
#772000
01
#776000
b1000011 <
b11 :
b110 F
11
#780000
01
#784000
b10 .
b10 4
0D
b111 F
1(
1,
b1100001 <
b100 :
02
11
#788000
01
#792000
0A
b1110000 <
b101 :
17
b1000 F
1D
0#
11
#796000
01
#800000
15
1#
b1001 F
b0 +
b0 6
0(
0,
b111000 <
b110 :
11
#804000
01
#808000
05
b11100 <
b111 :
07
b10000110 M
0I
b0 F
11
#812000
01
#816000
0D
1E
b1 F
b1110 <
b1000 :
11
#820000
01
#824000
b11 .
b11 4
b111 <
b1001 :
1(
1,
b10 F
0E
0#
1$
11
#828000
01
#832000
0$
b11 F
17
0-
b111 >
b0 :
1B
1C
12
11
#836000
01
#840000
15
0C
1A
0B
b1 :
b111 +
b111 6
0(
0,
b100 F
1D
02
11
#844000
01
#848000
05
1#
b101 F
b11 J
1I
07
b10 :
0A
11
#852000
01
#856000
b11 <
b11 :
b110 F
11
#860000
01
#864000
b0 .
b0 4
0/
0D
b111 F
1(
1,
b1 <
b100 :
12
11
#868000
01
#872000
1A
b0 <
b101 :
17
b1000 F
1D
0#
02
11
#876000
01
#880000
15
1#
b1001 F
b0 +
b0 6
0(
0,
b1000000 <
b110 :
0A
11
#884000
01
#888000
05
b100000 <
b111 :
07
b1110111000 M
b0 J
0I
0G
b10000110 N
b0 F
11
#892000
01
#896000
0D
1E
b1 F
b10000 <
b1000 :
11
#900000
01
#904000
b1000 <
b1001 :
1(
1,
b10 F
1D
0E
0#
1$
11
#908000
01
#912000
1#
0$
b11 F
17
b1000 >
b0 :
1B
1C
11
#916000
01
#920000
15
0C
0B
b1 :
b1000 +
b1000 6
0(
0,
b100 F
0D
11
#924000
01
#928000
05
0#
b101 F
1I
07
0?
b10 :
12
11
#932000
01
#936000
1A
b100 <
b11 :
b110 F
02
11
#940000
01
#944000
b1 .
b1 4
1/
b111 F
1(
1,
b1000010 <
b100 :
0A
12
11
#948000
01
#952000
1A
b100001 <
b101 :
17
b1000 F
1D
02
11
#956000
01
#960000
15
1#
0D
b1001 F
b0 +
b0 6
0(
0,
b1010000 <
b110 :
0A
11
#964000
01
#968000
05
b101000 <
b111 :
07
b1 J
1G
b1110111000 N
b0 F
0#
11
#972000
01
#976000
1E
b1 F
b10100 <
b1000 :
12
11
#980000
01
